fastertags/__init__.py
fastertags/_elements.py
fastertags/_gen.py
fastertags/elements.json
fastertags/elements.py
fastertags/headers.py
fastertags/py.typed
fastertags/shorthands.py
frozen/__init__.py
frozen/_deepfreeze.py
frozen/_frozen.py
frozen/_frozendict.py
frozen/py.typed
frzn/__init__.py
frzn/_deepfreeze.py
frzn/_frozendict.py
frzn/py.typed
frzn-1.0.1.dist-info/LICENSE
frzn-1.0.1.dist-info/METADATA
frzn-1.0.1.dist-info/WHEEL
frzn-1.0.1.dist-info/top_level.txt
frzn-1.0.1.dist-info/RECORD
